web_extract_data/__init__.py
web_extract_data/client.py
web_extract_data/endpoints/__init__.py
web_extract_data/endpoints/links.py
web_extract_data/endpoints/next.py
web_extract_data/endpoints/scrape.py
web_extract_data/endpoints/search.py
web_extract_data-0.1.0.dist-info/licenses/LICENSE
web_extract_data-0.1.0.dist-info/METADATA
web_extract_data-0.1.0.dist-info/WHEEL
web_extract_data-0.1.0.dist-info/top_level.txt
web_extract_data-0.1.0.dist-info/RECORD
