Metadata-Version: 2.4
Name: web-extract-data
Version: 0.1.0
Summary: A Python package for extracting structured data from websites
Home-page: https://web.instantapi.ai/
Author: InstantAPI.ai
Author-email: help@instantapi.ai
Project-URL: Documentation, https://web.instantapi.ai/documentation/
Project-URL: Source, https://github.com/zeeb0tt/pip-web-extract-data
Project-URL: Bug Reports, https://github.com/zeeb0tt/pip-web-extract-data/issues
Keywords: web scraping,data extraction,html parsing,structured data,api client
Classifier: Programming Language :: Python :: 3
Classifier: Programming Language :: Python :: 3.9
Classifier: Programming Language :: Python :: 3.10
Classifier: Programming Language :: Python :: 3.11
Classifier: Programming Language :: Python :: 3.12
Classifier: Programming Language :: Python :: 3.13
Classifier: Programming Language :: Python :: 3.14
Classifier: License :: OSI Approved :: MIT License
Classifier: Operating System :: OS Independent
Classifier: Development Status :: 5 - Production/Stable
Classifier: Intended Audience :: Developers
Classifier: Topic :: Internet :: WWW/HTTP :: Browsers
Classifier: Topic :: Software Development :: Libraries :: Python Modules
Requires-Python: >=3.9
License-File: LICENSE
Requires-Dist: requests
Dynamic: author
Dynamic: author-email
Dynamic: classifier
Dynamic: description
Dynamic: description-content-type
Dynamic: home-page
Dynamic: keywords
Dynamic: license-file
Dynamic: project-url
Dynamic: requires-dist
Dynamic: requires-python
Dynamic: summary
